Metadata-Version: 1.1
Name: oxtest
Version: 0.1
Summary: Tools for testing with docker.
Home-page: http://github.com/aocks/oxtest
Author: Emin Martinian
Author-email: emin.martinian@gmail.com
License: custom
Keywords: testing continuous integration
Platform: UNKNOWN
Classifier: Development Status :: 3 - Alpha
Classifier: Intended Audience :: Developers
Classifier: Programming Language :: Python :: 3
